tradingsystems/__init__.py
tradingsystems/graphs.py
tradingsystems/systems.py
tradingsystems-1.0.1.dist-info/LICENSE
tradingsystems-1.0.1.dist-info/METADATA
tradingsystems-1.0.1.dist-info/WHEEL
tradingsystems-1.0.1.dist-info/top_level.txt
tradingsystems-1.0.1.dist-info/RECORD
