Metadata-Version: 2.2
Name: tradingsystems
Version: 1.0.1
Summary: End of day backtesting of Technical trading rules.
Home-page: https://github.com/GBERESEARCH/tradingsystems
Author: GBERESEARCH
Author-email: gberesearch@gmail.com
License: MIT
License-File: LICENSE
Requires-Dist: numpy>=1.16.2
Requires-Dist: pandas>=1.0.0
Requires-Dist: scipy>=1.4.1
Requires-Dist: norgatedata>=1.0.48
Requires-Dist: technicalmethods>=0.1.6
Requires-Dist: tradingsystemsdata>=1.0.1
Requires-Dist: yfinance>=0.2.40
Requires-Dist: requests>=2.24.0
Requires-Dist: matplotlib>=3.4.2
